{
  "generator-jhipster": {
    "applicationType": "monolith",
    "baseName": "erpSystem",
    "jhipsterVersion": "7.1.0",
    "skipClient": false,
    "skipServer": false,
    "skipUserManagement": false,
    "skipCheckLengthOfIdentifier": false,
    "skipFakeData": false,
    "jhiPrefix": "gha",
    "entitySuffix": "",
    "dtoSuffix": "DTO",
    "testFrameworks": ["protractor", "gatling", "cucumber"],
    "blueprints": [],
    "otherModules": [],
    "pages": [],
    "creationTimestamp": 1628589878069,
    "serviceDiscoveryType": "eureka",
    "reactive": false,
    "authenticationType": "jwt",
    "packageName": "io.github.erp",
    "serverPort": "8975",
    "cacheProvider": "ehcache",
    "enableHibernateCache": true,
    "databaseType": "sql",
    "devDatabaseType": "postgresql",
    "prodDatabaseType": "postgresql",
    "buildTool": "maven",
    "serverSideOptions": ["searchEngine:elasticsearch", "websocket:spring-websocket"],
    "websocket": "spring-websocket",
    "searchEngine": "elasticsearch",
    "messageBroker": false,
    "enableSwaggerCodegen": false,
    "clientFramework": "angularX",
    "withAdminUi": true,
    "clientTheme": "lux",
    "clientThemeVariant": "dark",
    "enableTranslation": false,
    "nativeLanguage": "en",
    "packageFolder": "io/github/erp",
    "jwtSecretKey": "YjcxYTNmZWI5Y2FiOGI1ZWNiODRkNjI1NmRjODliZDIyYjRhOTZjZGQ4MmFiMWU1MDdiZjY4MzA0ZDU5ZTQ0MTk2MDYwYzU2MTQ5OGU1MDYxOTRlNWQzNTMxZWEyZDU4NjBlZjFkZmQwZDdmNzQyNTQ3NzQxODc0ODRhODE1Mzc=",
    "devServerPort": 4200,
    "clientPackageManager": "npm",
    "languages": ["en", "fr"],
    "entities": [
      "FixedAssetAcquisition",
      "FixedAssetNetBookValue",
      "FixedAssetDepreciation",
      "FileType",
      "FileUpload",
      "MessageToken",
      "Invoice",
      "Payment",
      "Dealer",
      "PaymentCalculation",
      "PaymentRequisition",
      "TaxReference",
      "TaxRule",
      "PaymentCategory"
    ]
  }
}
